resume_cli_generator-1.0.1.dist-info/licenses/LICENSE
resume_generator/__init__.py
resume_generator/cli.py
resume_generator/templates/resume_template.html
resume_cli_generator-1.0.1.dist-info/METADATA
resume_cli_generator-1.0.1.dist-info/WHEEL
resume_cli_generator-1.0.1.dist-info/entry_points.txt
resume_cli_generator-1.0.1.dist-info/top_level.txt
resume_cli_generator-1.0.1.dist-info/RECORD
