Metadata-Version: 2.4
Name: resume-cli-generator
Version: 1.0.1
Summary: A CLI tool to generate professional resumes in PDF format
Home-page: https://github.com/Vaishvik-Jaiswal/resume-cli-generator
Author: Vaishvik Jaiswal
Author-email: Vaishvik Jaiswal <vaishvikjaiswal05726@gmail.com>
License: MIT License
Project-URL: Homepage, https://github.com/Vaishvik-Jaiswal/resume-cli-generator
Project-URL: Repository, https://github.com/Vaishvik-Jaiswal/resume-cli-generator.git
Project-URL: Bug Tracker, https://github.com/Vaishvik-Jaiswal/resume-cli-generator/issues
Classifier: Development Status :: 4 - Beta
Classifier: Intended Audience :: End Users/Desktop
Classifier: License :: OSI Approved :: MIT License
Classifier: Operating System :: OS Independent
Classifier: Programming Language :: Python :: 3
Classifier: Programming Language :: Python :: 3.7
Classifier: Programming Language :: Python :: 3.8
Classifier: Programming Language :: Python :: 3.9
Classifier: Programming Language :: Python :: 3.10
Classifier: Programming Language :: Python :: 3.11
Requires-Python: >=3.7
License-File: LICENSE
Requires-Dist: jinja2>=3.0.0
Requires-Dist: weasyprint>=54.0
Requires-Dist: importlib-resources>=1.3.0; python_version < "3.9"
Dynamic: author
Dynamic: home-page
Dynamic: license-file
Dynamic: requires-python
